simple_bcrypt.py
simple_bcrypt-0.1.0.dist-info/DESCRIPTION.rst
simple_bcrypt-0.1.0.dist-info/METADATA
simple_bcrypt-0.1.0.dist-info/RECORD
simple_bcrypt-0.1.0.dist-info/WHEEL
simple_bcrypt-0.1.0.dist-info/metadata.json
simple_bcrypt-0.1.0.dist-info/top_level.txt
