Metadata-Version: 2.0
Name: simple-bcrypt
Version: 0.1.0
Summary: Bcrypt hashing for Flask, Sanic, Quart and Eve.
Home-page: https://github.com/shopnilsazal/simple-bcrypt
Author: Rafiqul Haasan
Author-email: shopnilsazal@gmail.com
License: BSD
Platform: any
Classifier: Environment :: Web Environment
Classifier: Intended Audience :: Developers
Classifier: License :: OSI Approved :: BSD License
Classifier: Operating System :: OS Independent
Classifier: Programming Language :: Python
Classifier: Programming Language :: Python :: 3
Classifier: Programming Language :: Python :: 3.3
Classifier: Programming Language :: Python :: 3.4
Classifier: Programming Language :: Python :: 3.5
Classifier: Programming Language :: Python :: 3.6
Classifier: Topic :: Internet :: WWW/HTTP :: Dynamic Content
Classifier: Topic :: Software Development :: Libraries :: Python Modules
Requires-Dist: bcrypt (>=3.1.1)
